{
  "META": {
    "graphic_title": "Migrant farmworker “streams”",
    "prose": "This map shows the three, generally accepted “migrant streams” in which farmworkers tend to travel to harvest crops seasonally. Each stream begins and ends in one of three “sending states,” Florida, Texas or California.",
    "source": "U.S. Department of Health & Human Services, Migrant Head Start Program",
    "source_url": "https://eclkc.ohs.acf.hhs.gov/definition/migrant-seasonal-head-start-programs",
    "credit": "Mike Fisher | San Antonio Express-News"
  }
}